{
  "/(user)/page": "app/(user)/page.js",
  "/_not-found/page": "app/_not-found/page.js",
  "/favicon.ico/route": "app/favicon.ico/route.js",
  "/(admin)/admin/dashboard/page": "app/(admin)/admin/dashboard/page.js",
  "/(admin)/admin/comment/page": "app/(admin)/admin/comment/page.js",
  "/(user)/product/[slug]/page": "app/(user)/product/[slug]/page.js",
  "/(user)/category/[slug]/page": "app/(user)/category/[slug]/page.js",
  "/(admin)/admin/auth/logout/page": "app/(admin)/admin/auth/logout/page.js",
  "/(admin)/admin/auth/login/page": "app/(admin)/admin/auth/login/page.js",
  "/(admin)/admin/products/add/page": "app/(admin)/admin/products/add/page.js"
}